odoo/addons/pos_multiple_control/README.rst
odoo/addons/pos_multiple_control/__init__.py
odoo/addons/pos_multiple_control/__manifest__.py
odoo/addons/pos_multiple_control/demo/account_account.xml
odoo/addons/pos_multiple_control/demo/account_bank_statement_cashbox.xml
odoo/addons/pos_multiple_control/demo/account_journal.xml
odoo/addons/pos_multiple_control/demo/pos_config.xml
odoo/addons/pos_multiple_control/demo/pos_move_reason.xml
odoo/addons/pos_multiple_control/demo/res_groups.xml
odoo/addons/pos_multiple_control/i18n/es.po
odoo/addons/pos_multiple_control/i18n/fr.po
odoo/addons/pos_multiple_control/i18n/pos_multiple_control.pot
odoo/addons/pos_multiple_control/models/__init__.py
odoo/addons/pos_multiple_control/models/account_bank_statement.py
odoo/addons/pos_multiple_control/models/account_journal.py
odoo/addons/pos_multiple_control/models/pos_config.py
odoo/addons/pos_multiple_control/models/pos_session.py
odoo/addons/pos_multiple_control/readme/CONFIGURE.rst
odoo/addons/pos_multiple_control/readme/CONTRIBUTORS.rst
odoo/addons/pos_multiple_control/readme/DESCRIPTION.rst
odoo/addons/pos_multiple_control/static/description/account_journal_config.png
odoo/addons/pos_multiple_control/static/description/change_starting_balance.gif
odoo/addons/pos_multiple_control/static/description/configure_cashbox_in_journal.gif
odoo/addons/pos_multiple_control/static/description/end_session_balance_automatic_solve.gif
odoo/addons/pos_multiple_control/static/description/end_session_set_balance.gif
odoo/addons/pos_multiple_control/static/description/icon.png
odoo/addons/pos_multiple_control/static/description/index.html
odoo/addons/pos_multiple_control/static/description/open_new_session.png
odoo/addons/pos_multiple_control/static/description/pos_session.png
odoo/addons/pos_multiple_control/static/description/pos_session_config.png
odoo/addons/pos_multiple_control/tests/__init__.py
odoo/addons/pos_multiple_control/tests/test_pos_multiple_control.py
odoo12_addon_pos_multiple_control-12.0.1.3.1.dist-info/METADATA
odoo12_addon_pos_multiple_control-12.0.1.3.1.dist-info/WHEEL
odoo12_addon_pos_multiple_control-12.0.1.3.1.dist-info/top_level.txt
odoo12_addon_pos_multiple_control-12.0.1.3.1.dist-info/RECORD
