Metadata-Version: 2.1
Name: odoo12-addon-pos-multiple-control
Version: 12.0.1.3.1
Summary: Allow user to control each statement and add extra checks
Home-page: https://github.com/OCA/pos
Author: GRAP, Odoo Community Association (OCA)
Author-email: support@odoo-community.org
License: AGPL-3
Platform: UNKNOWN
Classifier: Programming Language :: Python
Classifier: Framework :: Odoo
Classifier: Framework :: Odoo :: 12.0
Classifier: License :: OSI Approved :: GNU Affero General Public License v3
Requires-Python: >=3.5
Requires-Dist: odoo12-addon-pos-cash-move-reason
Requires-Dist: odoo (<12.1dev,>=12.0a)
